docs/gen_tree.py
pyx3270/__init__.py
pyx3270/__main__.py
pyx3270/cli.py
pyx3270/emulator.py
pyx3270/exceptions.py
pyx3270/iemulator.py
pyx3270/logging_config.py
pyx3270/offline.py
pyx3270/py.typed
pyx3270/server.py
pyx3270/state.py
pyx3270/tn3270.py
pyx3270/x3270_commands.py
pyx3270/bin/start.bin
pyx3270/bin/start.bin.bak
pyx3270/bin/linux/s3270
pyx3270/bin/linux/x3270
pyx3270/bin/windows/wc3270.exe
pyx3270/bin/windows/ws3270.exe
pyx3270/hook/__init__.py
pyx3270/hook/hook-pyx3270.py
site/gen_tree.py
tests/__init__.py
tests/conftest.py
tests/test_cli.py
tests/test_emulator.py
tests/test_exceptions.py
tests/test_offline.py
tests/test_server.py
pyx3270-0.1.4.dist-info/METADATA
pyx3270-0.1.4.dist-info/WHEEL
pyx3270-0.1.4.dist-info/entry_points.txt
pyx3270-0.1.4.dist-info/top_level.txt
pyx3270-0.1.4.dist-info/RECORD
