Metadata-Version: 2.1
Name: pyx3270
Version: 0.1.4
Summary: Uma interface comum utilizada para automações de terminais 3270 da IBM.
Author-email: MatheusLPolidoro <mattpolidoro4@gmail.com>
Project-URL: Documentation, https://matheuslpolidoro.github.io/pyx3270/
Project-URL: Source Code, https://github.com/MatheusLPolidoro/pyx3270
Project-URL: Bug Tracker, https://github.com/MatheusLPolidoro/pyx3270/issues
Requires-Python: <=3.14,>=3.8
Requires-Dist: click==8.1.8
Requires-Dist: colorama==0.4.6
Requires-Dist: Pygments==2.19.1
Requires-Dist: rich==14.0.0
Requires-Dist: shellingham==1.5.4
Requires-Dist: typer==0.15.3
Requires-Dist: typing-extensions==4.13.2
